cleartrack/__init__.py
cleartrack/cli.py
cleartrack-1.0.2.dist-info/licenses/LICENSE
cleartrack-1.0.2.dist-info/METADATA
cleartrack-1.0.2.dist-info/WHEEL
cleartrack-1.0.2.dist-info/entry_points.txt
cleartrack-1.0.2.dist-info/top_level.txt
cleartrack-1.0.2.dist-info/RECORD
