Metadata-Version: 2.4
Name: cleartrack
Version: 1.0.2
Summary: A fun CLI tool to track how often you clear your terminal.
Author-email: Anil Raj Rimal <anilrajrimal@gmail.com>
License-Expression: MIT
Requires-Python: >=3.6
License-File: LICENSE
Dynamic: license-file
